pyprofile/__init__.py
pyprofile/profiler.py
pyprofile/contrib/__init__.py
pyprofile/contrib/django/__init__.py
pyprofile/contrib/django/middleware.py
pyprofile/contrib/django/sql_profiler.py
pyprofile/fixtures/__init__.py
pyprofile-0.1.2.dist-info/LICENSE
pyprofile-0.1.2.dist-info/METADATA
pyprofile-0.1.2.dist-info/WHEEL
pyprofile-0.1.2.dist-info/top_level.txt
pyprofile-0.1.2.dist-info/RECORD
