Metadata-Version: 2.1
Name: pyprofile
Version: 0.1.2
Summary: Python profiling and visualizing package.
Home-page: https://github.com/anudeepsamaiya/pyprofile
Author: Anudeep Samaiya
Author-email: anudeepsamaiya@gmail.com
License: UNKNOWN
Platform: UNKNOWN
Classifier: Programming Language :: Python :: 3
Classifier: License :: OSI Approved :: MIT License
Classifier: Operating System :: OS Independent
Requires-Python: >=3.6
